symfeat/__init__.py
symfeat/__version__.py
symfeat/symfeat.py
symfeat-0.4.5.dist-info/DESCRIPTION.rst
symfeat-0.4.5.dist-info/METADATA
symfeat-0.4.5.dist-info/RECORD
symfeat-0.4.5.dist-info/WHEEL
symfeat-0.4.5.dist-info/metadata.json
symfeat-0.4.5.dist-info/top_level.txt
