Metadata-Version: 2.0
Name: symfeat
Version: 0.4.5
Summary: Ruled based feature engineering for regression
Home-page: https://github.com/ohjeah/symfeat
Author: Markus Quade
Author-email: info@markusqua.de
License: MIT
Platform: UNKNOWN
Classifier: Programming Language :: Python
Classifier: Programming Language :: Python :: 3.5
Classifier: Programming Language :: Python :: 3.6
Requires-Dist: joblib
Requires-Dist: numpy
Requires-Dist: sympy
Requires-Dist: toolz
